paramlib/__init__.py
paramlib/config_params.py
paramlib/global_parameters.py
paramlib-3.4.10.dist-info/licenses/LICENSE
paramlib-3.4.10.dist-info/METADATA
paramlib-3.4.10.dist-info/WHEEL
paramlib-3.4.10.dist-info/top_level.txt
paramlib-3.4.10.dist-info/RECORD
