Metadata-Version: 2.4
Name: paramlib
Version: 3.4.10
Summary: A Python library for managing configuration parameters and constants, centralizing access to application-wide settings and global constants
Author-email: Jon Ander Gabantxo <jagabantxo@gmail.com>
License: MIT License
Project-URL: Homepage, https://github.com/EusDancerDev/paramlib
Project-URL: Documentation, https://github.com/EusDancerDev/paramlib#readme
Project-URL: Repository, https://github.com/EusDancerDev/paramlib.git
Project-URL: Bug Reports, https://github.com/EusDancerDev/paramlib/issues
Keywords: configuration,parameters,constants,settings,global variables
Classifier: Development Status :: 4 - Beta
Classifier: Intended Audience :: Developers
Classifier: Programming Language :: Python :: 3
Classifier: Programming Language :: Python :: 3.10
Classifier: Programming Language :: Python :: 3.11
Classifier: Programming Language :: Python :: 3.12
Classifier: Operating System :: OS Independent
Classifier: Topic :: Software Development :: Libraries :: Python Modules
Classifier: Topic :: Utilities
Requires-Python: >=3.10
License-File: LICENSE
Requires-Dist: pandas>=1.3.0
Requires-Dist: numpy>=1.21.0
Provides-Extra: dev
Requires-Dist: pytest>=7.0.0; extra == "dev"
Requires-Dist: pytest-cov>=4.0.0; extra == "dev"
Requires-Dist: black>=23.0.0; extra == "dev"
Requires-Dist: isort>=5.0.0; extra == "dev"
Requires-Dist: mypy>=1.0.0; extra == "dev"
Requires-Dist: flake8>=6.0.0; extra == "dev"
Dynamic: license-file
